obriscli/__init__.py
obriscli/__main__.py
obriscli/client_factory.py
obriscli/execeptions.py
obriscli/logger.py
obriscli/utilities.py
obriscli/clients/__init__.py
obriscli/clients/base_client.py
obriscli/clients/response_mappers.py
obriscli/clients/applications/__init__.py
obriscli/clients/applications/application_client.py
obriscli/clients/applications/application_response_mapper.py
obriscli/clients/applications/cloud_application_client.py
obriscli/clients/applications/exceptions.py
obriscli/clients/applications/routes.py
obriscli/clients/certificates/__init__.py
obriscli/clients/certificates/ssl_tls/__init__.py
obriscli/clients/certificates/ssl_tls/routes.py
obriscli/clients/certificates/ssl_tls/ssl_tls_certificate_client.py
obriscli/clients/certificates/ssl_tls/ssl_tls_response_mapper.py
obriscli/clients/credentials/__init__.py
obriscli/clients/credentials/github/__init__.py
obriscli/clients/credentials/github/github_credential_client.py
obriscli/clients/credentials/github/github_credential_response_mapper.py
obriscli/clients/credentials/github/routes.py
obriscli/clients/env_vars/__init__.py
obriscli/clients/env_vars/env_vars_client.py
obriscli/clients/env_vars/env_vars_response_mapper.py
obriscli/clients/env_vars/routes.py
obriscli/clients/notify/__init__.py
obriscli/clients/notify/notify_client.py
obriscli/clients/notify/routes.py
obriscli/clients/processes/__init__.py
obriscli/clients/processes/process_client.py
obriscli/clients/processes/process_response_mapper.py
obriscli/clients/processes/routes.py
obriscli/clients/repos/__init__.py
obriscli/clients/repos/repo_client.py
obriscli/clients/repos/repo_response_mapper.py
obriscli/clients/repos/routes.py
obriscli/clients/users/__init__.py
obriscli/clients/users/routes.py
obriscli/clients/users/user_client.py
obriscli/clients/users/user_response_mapper.py
obriscli/clients/webservers/__init__.py
obriscli/clients/webservers/routes.py
obriscli/clients/webservers/webserver_client.py
obris-0.1.10.dist-info/LICENSE
obris-0.1.10.dist-info/METADATA
obris-0.1.10.dist-info/WHEEL
obris-0.1.10.dist-info/entry_points.txt
obris-0.1.10.dist-info/top_level.txt
obris-0.1.10.dist-info/RECORD
