Metadata-Version: 2.1
Name: obris
Version: 0.1.10
Summary: Obris CLI for managing infrastructure independent of your cloud provider.
Author-email: Obris <dev@obris.io>
Requires-Python: >=3.7
License-File: LICENSE
Requires-Dist: click >=8.1.7
Requires-Dist: attrs >=23.1.0
Requires-Dist: requests >=2.31.0
